{
  "basicInformation": {
    "fullName": "",
    "age": null,
    "weight": {
      "value": null,
      "unit": ""
    },
    "height": {
      "value": null,
      "unit": ""
    },
    "bloodType": ""
  },
  "dietaryPreferences": {
    "dietType": "",
    "dietTypeOther": "",
    "allergiesIntolerances": {
      "dairy": false,
      "eggs": false,
      "nuts": {
        "selected": false,
        "details": ""
      },
      "seafoodShellfish": false,
      "gluten": false,
      "soy": false,
      "other": {
        "selected": false,
        "details": ""
      }
    },
    "favoriteCuisines": {
      "italian": false,
      "mexican": false,
      "indian": false,
      "chinese": false,
      "japanese": false,
      "thai": false,
      "mediterranean": false,
      "american": false,
      "middleEastern": false,
      "other": {
        "selected": false,
        "details": ""
      }
    },
    "spiceTolerance": null,
    "dislikedFoods": ""
  },
  "medicalConditions": {
    "diabetes": {
      "selected": false,
      "type": ""
    },
    "celiacDisease": false,
    "inflammatoryBowelDisease": {
      "selected": false,
      "type": ""
    },
    "hypertension": false,
    "cardiovascularDisease": false,
    "chronicKidneyDisease": false,
    "acidReflux": false,
    "irritableBowelSyndrome": false,
    "gout": false,
    "phenylketonuria": false,
    "liverDisease": false,
    "other": {
      "selected": false,
      "details": ""
    }
  },
  "dietaryGoals": {
    "weightLoss": false,
    "weightGain": false,
    "maintenance": false,
    "increasedEnergy": false,
    "betterDigestion": false,
    "improvedSleep": false,
    "muscleBuilding": false,
    "other": {
      "selected": false,
      "details": ""
    }
  },
  "lifestyleInformation": {
    "activityLevel": "",
    "averageSleepHours": null,
    "stressLevel": null,
    "waterIntake": ""
  },
  "mealPreferences": {
    "mealsPerDay": null,
    "snackBetweenMeals": false,
    "preferredMealPrepTime": "",
    "cookingFacilities": {
      "stove": false,
      "oven": false,
      "microwave": false,
      "blender": false,
      "foodProcessor": false
    }
  }
}